{
  "main": {
    "id": "16e86aa14f3ada93",
    "type": "split",
    "children": [
      {
        "id": "5a056ee0cbe12cb3",
        "type": "tabs",
        "children": [
          {
            "id": "13fcf24f269ef861",
            "type": "leaf",
            "state": {
              "type": "markdown",
              "state": {
                "file": "Spring/SQL/DELETE.md",
                "mode": "source",
                "source": false
              }
            }
          },
          {
            "id": "d4cd0ccc4a179caf",
            "type": "leaf",
            "state": {
              "type": "markdown",
              "state": {
                "file": "Spring/CORS(Cross-Origin Resource Sharing Policy).md",
                "mode": "source",
                "source": false
              }
            }
          },
          {
            "id": "abefa52c6235ab22",
            "type": "leaf",
            "state": {
              "type": "graph",
              "state": {}
            }
          }
        ],
        "currentTab": 2
      }
    ],
    "direction": "vertical"
  },
  "left": {
    "id": "14e5e9b3a58d9471",
    "type": "split",
    "children": [
      {
        "id": "806c813cde3e8f87",
        "type": "tabs",
        "children": [
          {
            "id": "cc65f794136683d2",
            "type": "leaf",
            "state": {
              "type": "file-explorer",
              "state": {
                "sortOrder": "alphabetical"
              }
            }
          },
          {
            "id": "11933cf121731d8b",
            "type": "leaf",
            "state": {
              "type": "search",
              "state": {
                "query": "",
                "matchingCase": false,
                "explainSearch": false,
                "collapseAll": false,
                "extraContext": false,
                "sortOrder": "alphabetical"
              }
            }
          },
          {
            "id": "3b028e36612f48a5",
            "type": "leaf",
            "state": {
              "type": "bookmarks",
              "state": {}
            }
          }
        ]
      }
    ],
    "direction": "horizontal",
    "width": 300
  },
  "right": {
    "id": "8772200791b39149",
    "type": "split",
    "children": [
      {
        "id": "00d3a504b2b22dd1",
        "type": "tabs",
        "children": [
          {
            "id": "7444b7642164e5be",
            "type": "leaf",
            "state": {
              "type": "backlink",
              "state": {
                "collapseAll": false,
                "extraContext": false,
                "sortOrder": "alphabetical",
                "showSearch": false,
                "searchQuery": "",
                "backlinkCollapsed": false,
                "unlinkedCollapsed": true
              }
            }
          },
          {
            "id": "9a3b959305cd4dfe",
            "type": "leaf",
            "state": {
              "type": "outgoing-link",
              "state": {
                "linksCollapsed": false,
                "unlinkedCollapsed": true
              }
            }
          },
          {
            "id": "7eb5c01b7986a90a",
            "type": "leaf",
            "state": {
              "type": "tag",
              "state": {
                "sortOrder": "frequency",
                "useHierarchy": true
              }
            }
          },
          {
            "id": "e3824bbbdc8b43a1",
            "type": "leaf",
            "state": {
              "type": "outline",
              "state": {}
            }
          }
        ]
      }
    ],
    "direction": "horizontal",
    "width": 300,
    "collapsed": true
  },
  "left-ribbon": {
    "hiddenItems": {
      "switcher:퀵 스위처 열기": false,
      "graph:그래프 뷰 열기": false,
      "canvas:새 캔버스 만들기": false,
      "daily-notes:오늘의 데일리 노트 열기": false,
      "templates:템플릿 삽입": false,
      "command-palette:명령어 팔레트 열기": false,
      "obsidian-file-cleaner:Clean files": false
    }
  },
  "active": "abefa52c6235ab22",
  "lastOpenFiles": [
    "Java/어노테이션(Annotation).md",
    "Java/클래스(Class).md",
    "Spring/객체(Object).md",
    "Spring/CORS(Cross-Origin Resource Sharing Policy).md",
    "WebMvcConfigurer.md",
    "Spring/템플릿(Template).md",
    "@ControllerAdvice.md",
    "Spring/@Component.md",
    "Spring/@RestControllerAdvice.md",
    "Spring/SQL/WHERE.md",
    "Spring/SQL/SQL.md",
    "Spring/SQL/기호 문자(Wildcard Character).md",
    "LIKE.md",
    "Spring/SQL/INSERT.md",
    "Spring/SQL/GROUP.md",
    "Spring/SQL/DROP.md",
    "Spring/SQL/CREATE.md",
    "Spring/JPA/Paging.md",
    "Spring/JPA/JPA(Java Persistence API).md",
    "Java/Stream/IntStream.md",
    "Java/Stream/boxed().md",
    "Java/Stream/Stream.of().md",
    "Spring/JPA/lombok/@Builder.md",
    "Spring/JPA/lombok/@SuperBuilder.md",
    "Spring/빌더 패턴(Builder Pattern).md",
    "Spring/@Value.md",
    "image/Pasted image 20240229173714.png",
    "image/Pasted image 20240229150251.png",
    "image/Pasted image 20240226020336.png",
    "image/Pasted image 20240226020200.png",
    "Spring/무제 폴더",
    "image/Pasted image 20240219034238.png",
    "image/Pasted image 20240213224850.png",
    "image/Pasted image 20240206212431.png",
    "image/Pasted image 20231101224851.png",
    "image/Pasted image 20231012205605.png",
    "image/Pasted image 20231012205519.png",
    "Spring/Servlet",
    "Spring/DBCP",
    "Spring/JDBC",
    "Java/Collection",
    "Java/Stream",
    "Spring/JPA/CrudRepository",
    "Spring/Test",
    "Spring/Docker",
    "Spring/JSP/mustache",
    "무제 파일.canvas"
  ]
}