{
  "main": {
    "id": "16e86aa14f3ada93",
    "type": "split",
    "children": [
      {
        "id": "5a056ee0cbe12cb3",
        "type": "tabs",
        "children": [
          {
            "id": "94cc9ad73d838f85",
            "type": "leaf",
            "state": {
              "type": "markdown",
              "state": {
                "file": "Spring/SQL/다대일(ManyToOne).md",
                "mode": "source",
                "source": false
              }
            }
          },
          {
            "id": "fb68d644cb93a811",
            "type": "leaf",
            "state": {
              "type": "markdown",
              "state": {
                "file": "Spring/Test/@WebMvcTest.md",
                "mode": "source",
                "source": false
              }
            }
          },
          {
            "id": "4045aec963db931e",
            "type": "leaf",
            "state": {
              "type": "markdown",
              "state": {
                "file": "Spring/JSP/Thymeleaf.md",
                "mode": "source",
                "source": false
              }
            }
          },
          {
            "id": "13fcf24f269ef861",
            "type": "leaf",
            "state": {
              "type": "graph",
              "state": {}
            }
          }
        ],
        "currentTab": 2
      }
    ],
    "direction": "vertical"
  },
  "left": {
    "id": "14e5e9b3a58d9471",
    "type": "split",
    "children": [
      {
        "id": "806c813cde3e8f87",
        "type": "tabs",
        "children": [
          {
            "id": "cc65f794136683d2",
            "type": "leaf",
            "state": {
              "type": "file-explorer",
              "state": {
                "sortOrder": "alphabetical"
              }
            }
          },
          {
            "id": "11933cf121731d8b",
            "type": "leaf",
            "state": {
              "type": "search",
              "state": {
                "query": "",
                "matchingCase": false,
                "explainSearch": false,
                "collapseAll": false,
                "extraContext": false,
                "sortOrder": "alphabetical"
              }
            }
          },
          {
            "id": "3b028e36612f48a5",
            "type": "leaf",
            "state": {
              "type": "bookmarks",
              "state": {}
            }
          }
        ]
      }
    ],
    "direction": "horizontal",
    "width": 300
  },
  "right": {
    "id": "8772200791b39149",
    "type": "split",
    "children": [
      {
        "id": "00d3a504b2b22dd1",
        "type": "tabs",
        "children": [
          {
            "id": "7444b7642164e5be",
            "type": "leaf",
            "state": {
              "type": "backlink",
              "state": {
                "file": "Spring/JSP/Thymeleaf.md",
                "collapseAll": false,
                "extraContext": false,
                "sortOrder": "alphabetical",
                "showSearch": false,
                "searchQuery": "",
                "backlinkCollapsed": false,
                "unlinkedCollapsed": true
              }
            }
          },
          {
            "id": "9a3b959305cd4dfe",
            "type": "leaf",
            "state": {
              "type": "outgoing-link",
              "state": {
                "file": "Spring/JSP/Thymeleaf.md",
                "linksCollapsed": false,
                "unlinkedCollapsed": true
              }
            }
          },
          {
            "id": "7eb5c01b7986a90a",
            "type": "leaf",
            "state": {
              "type": "tag",
              "state": {
                "sortOrder": "frequency",
                "useHierarchy": true
              }
            }
          },
          {
            "id": "e3824bbbdc8b43a1",
            "type": "leaf",
            "state": {
              "type": "outline",
              "state": {
                "file": "Spring/JSP/Thymeleaf.md"
              }
            }
          }
        ]
      }
    ],
    "direction": "horizontal",
    "width": 300,
    "collapsed": true
  },
  "left-ribbon": {
    "hiddenItems": {
      "switcher:퀵 스위처 열기": false,
      "graph:그래프 뷰 열기": false,
      "canvas:새 캔버스 만들기": false,
      "daily-notes:오늘의 데일리 노트 열기": false,
      "templates:템플릿 삽입": false,
      "command-palette:명령어 팔레트 열기": false,
      "obsidian-file-cleaner:Clean files": false
    }
  },
  "active": "4045aec963db931e",
  "lastOpenFiles": [
    "Spring/템플릿(Template).md",
    "Spring/JSP/Thymeleaf.md",
    "인텔리제이 단축키.md",
    "Spring/Test/MockMvc.md",
    "Spring/Test/TDD(Test Driven Development).md",
    "Spring/Test/@Test.md",
    "Spring/Test/테스트 메서드(Test Method).md",
    "Spring/Test/@MockBean.md",
    "Spring/Test/Given-When-Then.md",
    "Spring/Test/@WebMvcTest.md",
    "Spring/@ApplicationContext(AppConfig.class).md",
    "Spring/SQL/?(Placeholder).md",
    "Spring/JPA/queryDSL.md",
    "ERD(Entity Relationship Diagram).md",
    "Spring/SQL/속성(Attribute).md",
    "Spring/SQL/연관 관계(Relationships).md",
    "Spring/API(Application Programming Interface).md",
    "Spring/JPA/엔티티(Entity).md",
    "Spring/SQL/다대다(ManyToMany).md",
    "Spring/SQL/레코드(Record).md",
    "Spring/SQL/다대일(ManyToOne).md",
    "Spring/SQL/일대다(OnetoMany).md",
    "Spring/JPA/@OneToMany.md",
    "참조 타입(Reference Type).md",
    "Java/HashMap.md",
    "Java/Collection/Iterator().md",
    "Spring/무제 폴더",
    "image/Pasted image 20240219034238.png",
    "image/Pasted image 20240213224850.png",
    "image/Pasted image 20240206212431.png",
    "image/Pasted image 20231101224851.png",
    "image/Pasted image 20231012205605.png",
    "image/Pasted image 20231012205519.png",
    "image/Pasted image 20231012172903.png",
    "image/Pasted image 20231012133632.png",
    "image/Pasted image 20231005111135.png",
    "image/Pasted image 20240219022021.png",
    "Spring/Servlet",
    "Spring/DBCP",
    "Spring/JDBC",
    "Java/Collection",
    "Java/Stream",
    "Spring/JPA/CrudRepository",
    "Spring/Test",
    "Spring/Docker",
    "Spring/JSP/mustache",
    "무제 파일.canvas"
  ]
}